{"tracks":[{"imageUrl":"https://i.scdn.co/image/ab67616d0000b273ceb160561269ab00b1df9678","title":"Tim's Intro","artist":"Brent Faiyaz","albumName":"Larger Than Life","albumType":"album","releaseDate":"2023-10-27","duration":124552,"uri":"spotify:track:7qzQfE2se3Ai5reZcxs920","id":"7qzQfE2se3Ai5reZcxs920","popularity":53,"previewUrl":""},{"imageUrl":"https://i.scdn.co/image/ab67616d0000b27309d6ed214f03fbb663e46531","title":"luther (with sza)","artist":"Kendrick Lamar","albumName":"GNX","albumType":"album","releaseDate":"2024-11-21","duration":177598,"uri":"spotify:track:2CGNAOSuO1MEFCbBRgUzjd","id":"2CGNAOSuO1MEFCbBRgUzjd","popularity":87,"previewUrl":""},{"imageUrl":"https://i.scdn.co/image/ab67616d0000b273124e9249fada4ff3c3a0739c","title":"Thought I Was Dead (feat. ScHoolboy Q & Santigold)","artist":"Tyler, The Creator","albumName":"CHROMAKOPIA","albumType":"album","releaseDate":"2024-10-28","duration":207272,"uri":"spotify:track:2aYHxnMF2umAavtgBvmkY1","id":"2aYHxnMF2umAavtgBvmkY1","popularity":80,"previewUrl":""},{"imageUrl":"https://i.scdn.co/image/ab67616d0000b273124e9249fada4ff3c3a0739c","title":"St. Chroma (feat. Daniel Caesar)","artist":"Tyler, The Creator","albumName":"CHROMAKOPIA","albumType":"album","releaseDate":"2024-10-28","duration":197019,"uri":"spotify:track:1QoyuMHNBe7lg3YW4Qtll4","id":"1QoyuMHNBe7lg3YW4Qtll4","popularity":84,"previewUrl":""},{"imageUrl":"https://i.scdn.co/image/ab67616d0000b273124e9249fada4ff3c3a0739c","title":"Like Him (feat. Lola Young)","artist":"Tyler, The Creator","albumName":"CHROMAKOPIA","albumType":"album","releaseDate":"2024-10-28","duration":278014,"uri":"spotify:track:6jbYpRPTEFl1HFKHk1IC0m","id":"6jbYpRPTEFl1HFKHk1IC0m","popularity":90,"previewUrl":""},{"imageUrl":"https://i.scdn.co/image/ab67616d0000b2732a525fbb15bb3876e5b46585","title":"too far close","artist":"Chase Shakur","albumName":"It'll Be Fine","albumType":"album","releaseDate":"2022-06-24","duration":180266,"uri":"spotify:track:1rKdNSA119ByMxI9chV5J6","id":"1rKdNSA119ByMxI9chV5J6","popularity":62,"previewUrl":""},{"imageUrl":"https://i.scdn.co/image/ab67616d0000b2737c68face1dc58127f3a7b1cc","title":"Always","artist":"Daniel Caesar","albumName":"NEVER ENOUGH","albumType":"album","releaseDate":"2023-04-07","duration":225312,"uri":"spotify:track:2LlOeW5rVcvl3QcPNPcDus","id":"2LlOeW5rVcvl3QcPNPcDus","popularity":79,"previewUrl":""},{"imageUrl":"https://i.scdn.co/image/ab67616d0000b273ceb160561269ab00b1df9678","title":"Last One Left (feat. Missy Elliott & Lil Gray)","artist":"Brent Faiyaz","albumName":"Larger Than Life","albumType":"album","releaseDate":"2023-10-27","duration":224598,"uri":"spotify:track:0cZ9HBGWLZJS7UHCgWXOTZ","id":"0cZ9HBGWLZJS7UHCgWXOTZ","popularity":58,"previewUrl":""},{"imageUrl":"https://i.scdn.co/image/ab67616d0000b273ceb160561269ab00b1df9678","title":"Forever Yours","artist":"Brent Faiyaz","albumName":"Larger Than Life","albumType":"album","releaseDate":"2023-10-27","duration":96368,"uri":"spotify:track:2JqkpMe2eJToJNHEqkJeCu","id":"2JqkpMe2eJToJNHEqkJeCu","popularity":76,"previewUrl":""},{"imageUrl":"https://i.scdn.co/image/ab67616d0000b273124e9249fada4ff3c3a0739c","title":"Sticky (feat. GloRilla, Sexyy Red & Lil Wayne)","artist":"Tyler, The Creator","albumName":"CHROMAKOPIA","albumType":"album","releaseDate":"2024-10-28","duration":255915,"uri":"spotify:track:3tFed7YsjGnIfxeLEQwx3R","id":"3tFed7YsjGnIfxeLEQwx3R","popularity":89,"previewUrl":""},{"imageUrl":"https://i.scdn.co/image/ab67616d0000b273124e9249fada4ff3c3a0739c","title":"Darling, I (feat. Teezo Touchdown)","artist":"Tyler, The Creator","albumName":"CHROMAKOPIA","albumType":"album","releaseDate":"2024-10-28","duration":253834,"uri":"spotify:track:0VaeksJaXy5R1nvcTMh3Xk","id":"0VaeksJaXy5R1nvcTMh3Xk","popularity":82,"previewUrl":""},{"imageUrl":"https://i.scdn.co/image/ab67616d0000b273d9985092cd88bffd97653b58","title":"gloria (with sza)","artist":"Kendrick Lamar","albumName":"GNX","albumType":"album","releaseDate":"2024-11-22","duration":287522,"uri":"spotify:track:0wgOhYnqZKjOHr6bmdz0aN","id":"0wgOhYnqZKjOHr6bmdz0aN","popularity":81,"previewUrl":""},{"imageUrl":"https://i.scdn.co/image/ab67616d0000b273d9985092cd88bffd97653b58","title":"heart pt. 6","artist":"Kendrick Lamar","albumName":"GNX","albumType":"album","releaseDate":"2024-11-22","duration":292461,"uri":"spotify:track:1SGvjfc85yzqKXsfKcCxn2","id":"1SGvjfc85yzqKXsfKcCxn2","popularity":81,"previewUrl":""},{"imageUrl":"https://i.scdn.co/image/ab67616d0000b273b245099fe26319344ddf6054","title":"DENIAL IS A RIVER","artist":"Doechii","albumName":"Alligator Bites Never Heal","albumType":"album","releaseDate":"2024-08-30","duration":159586,"uri":"spotify:track:1eTaznNW4Xxtx9za2SMTXB","id":"1eTaznNW4Xxtx9za2SMTXB","popularity":84,"previewUrl":""},{"imageUrl":"https://i.scdn.co/image/ab67616d0000b273b245099fe26319344ddf6054","title":"NISSAN ALTIMA","artist":"Doechii","albumName":"Alligator Bites Never Heal","albumType":"album","releaseDate":"2024-08-30","duration":126832,"uri":"spotify:track:2dKkVF2m160z0RNDN2dddc","id":"2dKkVF2m160z0RNDN2dddc","popularity":79,"previewUrl":""},{"imageUrl":"https://i.scdn.co/image/ab67616d0000b27382ea2e9e1858aa012c57cd45","title":"Die With A Smile","artist":"Lady Gaga","albumName":"Die With A Smile","albumType":"single","releaseDate":"2024-08-16","duration":251667,"uri":"spotify:track:2plbrEY59IikOBgBGLjaoe","id":"2plbrEY59IikOBgBGLjaoe","popularity":100,"previewUrl":""},{"imageUrl":"https://i.scdn.co/image/ab67616d0000b273c12a7e77f243d24e4d26d560","title":"Player Two - From \"Don't Tell Mom The Babysitter's Dead\"","artist":"Jordan Ward","albumName":"Player Two (From \"Don't Tell Mom The Babysitter's Dead\")","albumType":"single","releaseDate":"2024-04-12","duration":158057,"uri":"spotify:track:2k9cIkCVD4zotzFL6xj6hg","id":"2k9cIkCVD4zotzFL6xj6hg","popularity":56,"previewUrl":""},{"imageUrl":"https://i.scdn.co/image/ab67616d0000b2730995ea2da176fa94bedb71dd","title":"Sticky (feat. Childish Gambino & KIRBY)","artist":"Ni'jah","albumName":"Swarm","albumType":"single","releaseDate":"2023-03-17","duration":171706,"uri":"spotify:track:14adSLAL6WgvwH5snRF3gs","id":"14adSLAL6WgvwH5snRF3gs","popularity":33,"previewUrl":""}]}